{
  "minecraft:recipes/misc/iron_ingot_from_nuggets": {
    "criteria": {
      "has_at_least_9_iron_nugget": "2018-02-14 17:46:40 -0600"
    },
    "done": true
  },
  "minecraft:recipes/building_blocks/coal_block": {
    "criteria": {
      "has_at_least_9_coal": "2018-02-14 17:46:40 -0600"
    },
    "done": true
  },
  "minecraft:recipes/misc/yellow_dye_from_dandelion": {
    "criteria": {
      "has_yellow_flower": "2018-02-14 17:46:40 -0600"
    },
    "done": true
  },
  "minecraft:recipes/misc/light_blue_dye_from_blue_orchid": {
    "criteria": {
      "has_red_flower": "2018-02-14 17:46:40 -0600"
    },
    "done": true
  },
  "minecraft:adventure/adventuring_time": {
    "criteria": {
      "plains": "2018-02-14 17:46:40 -0600"
    },
    "done": false
  },
  "minecraft:story/root": {
    "criteria": {
      "crafting_table": "2018-02-14 17:46:40 -0600"
    },
    "done": true
  }
}